zps/__init__.py
zps-0.1.1.dist-info/LICENSE
zps-0.1.1.dist-info/METADATA
zps-0.1.1.dist-info/WHEEL
zps-0.1.1.dist-info/top_level.txt
zps-0.1.1.dist-info/RECORD
